SerializationOfClassesAndFuncs/__init__.py
SerializationOfClassesAndFuncs/base_serializer.py
SerializationOfClassesAndFuncs/dict_serializer.py
SerializationOfClassesAndFuncs/json_serializer.py
SerializationOfClassesAndFuncs/serializers_factory.py
SerializationOfClassesAndFuncs/type_constants.py
SerializationOfClassesAndFuncs/xml_serializer.py
serialization/__init__.py
serialization/base_serializer.py
serialization/dict_serializer.py
serialization/json_serializer.py
serialization/serializers_factory.py
serialization/type_constants.py
serialization/xml_serializer.py
SerializationOfClassesAndFuncs-0.1.1.dist-info/LICENSE
SerializationOfClassesAndFuncs-0.1.1.dist-info/METADATA
SerializationOfClassesAndFuncs-0.1.1.dist-info/WHEEL
SerializationOfClassesAndFuncs-0.1.1.dist-info/top_level.txt
SerializationOfClassesAndFuncs-0.1.1.dist-info/RECORD
